{"code": "ULG",
"content": [
{"date":"17.06.2018","code":"ULG","set":"Urza's Legacy","data":[{"name":"About Face","rarity":"Special","baseAvail":1792,"basePrice":0.01,"foilAvail":46,"foilPrice":0.2},{"name":"Angel's Trumpet","rarity":"Special","baseAvail":876,"basePrice":0.02,"foilAvail":13,"foilPrice":0.93},{"name":"Angelic Curator","rarity":"Special","baseAvail":1774,"basePrice":0.01,"foilAvail":35,"foilPrice":0.6},{"name":"Anthroplasm","rarity":"Special","baseAvail":934,"basePrice":0.02,"foilAvail":13,"foilPrice":4.45},{"name":"Archivist","rarity":"Special","baseAvail":909,"basePrice":0.05,"foilAvail":15,"foilPrice":8.85},{"name":"Aura Flux","rarity":"Special","baseAvail":901,"basePrice":0.02,"foilAvail":24,"foilPrice":2.5},{"name":"Avalanche Riders","rarity":"Special","baseAvail":967,"basePrice":0.1,"foilAvail":57,"foilPrice":3},{"name":"Beast of Burden","rarity":"Special","baseAvail":568,"basePrice":0.05,"foilAvail":23,"foilPrice":3.5},{"name":"Blessed Reversal","rarity":"Special","baseAvail":704,"basePrice":0.02,"foilAvail":21,"foilPrice":1.7},{"name":"Bloated Toad","rarity":"Special","baseAvail":1001,"basePrice":0.02,"foilAvail":1,"foilPrice":2.9},{"name":"Bone Shredder","rarity":"Special","baseAvail":1167,"basePrice":0.02,"foilAvail":26,"foilPrice":7.99},{"name":"Bouncing Beebles","rarity":"Special","baseAvail":1778,"basePrice":0.01,"foilAvail":25,"foilPrice":0.25},{"name":"Brink of Madness","rarity":"Special","baseAvail":869,"basePrice":0.02,"foilAvail":22,"foilPrice":0.95},{"name":"Burst of Energy","rarity":"Special","baseAvail":1856,"basePrice":0.01,"foilAvail":40,"foilPrice":0.15},{"name":"Cessation","rarity":"Special","baseAvail":1899,"basePrice":0.01,"foilAvail":35,"foilPrice":0.18},{"name":"Cloud of Faeries","rarity":"Special","baseAvail":2533,"basePrice":0.05,"foilAvail":81,"foilPrice":5.39},{"name":"Crawlspace","rarity":"Special","baseAvail":211,"basePrice":0.4,"foilAvail":21,"foilPrice":24.99},{"name":"Crop Rotation","rarity":"Special","baseAvail":770,"basePrice":0.8,"foilAvail":35,"foilPrice":59},{"name":"Damping Engine","rarity":"Special","baseAvail":709,"basePrice":0.05,"foilAvail":17,"foilPrice":2},{"name":"Darkwatch Elves","rarity":"Special","baseAvail":1162,"basePrice":0.02,"foilAvail":61,"foilPrice":0.47},{"name":"Defender of Chaos","rarity":"Special","baseAvail":1942,"basePrice":0.01,"foilAvail":33,"foilPrice":0.25},{"name":"Defender of Law","rarity":"Special","baseAvail":1758,"basePrice":0.01,"foilAvail":30,"foilPrice":0.1},{"name":"Defense Grid","rarity":"Special","baseAvail":398,"basePrice":1.9,"foilAvail":31,"foilPrice":34.98},{"name":"Defense of the Heart","rarity":"Special","baseAvail":495,"basePrice":4,"foilAvail":33,"foilPrice":29.99},{"name":"Delusions of Mediocrity","rarity":"Special","baseAvail":781,"basePrice":0.05,"foilAvail":17,"foilPrice":4.48},{"name":"Deranged Hermit","rarity":"Special","baseAvail":280,"basePrice":2.49,"foilAvail":23,"foilPrice":60},{"name":"Devout Harpist","rarity":"Special","baseAvail":1773,"basePrice":0.01,"foilAvail":35,"foilPrice":0.75},{"name":"Engineered Plague","rarity":"Special","baseAvail":2325,"basePrice":0.02,"foilAvail":62,"foilPrice":3},{"name":"Erase","rarity":"Special","baseAvail":2112,"basePrice":0.01,"foilAvail":67,"foilPrice":0.92},{"name":"Eviscerator","rarity":"Special","baseAvail":893,"basePrice":0.02,"foilAvail":27,"foilPrice":1.97},{"name":"Expendable Troops","rarity":"Special","baseAvail":1869,"basePrice":0.01,"foilAvail":46,"foilPrice":0.05},{"name":"Faerie Conclave","rarity":"Special","baseAvail":870,"basePrice":0.02,"foilAvail":35,"foilPrice":7},{"name":"Fleeting Image","rarity":"Special","baseAvail":973,"basePrice":0.04,"foilAvail":42,"foilPrice":1.24},{"name":"Fog of Gnats","rarity":"Special","baseAvail":1779,"basePrice":0.01,"foilAvail":46,"foilPrice":0.25},{"name":"Forbidding Watchtower","rarity":"Special","baseAvail":1020,"basePrice":0.02,"foilAvail":67,"foilPrice":1.5},{"name":"Frantic Search","rarity":"Special","baseAvail":1573,"basePrice":0.05,"foilAvail":39,"foilPrice":9},{"name":"Gang of Elk","rarity":"Special","baseAvail":1026,"basePrice":0.02,"foilAvail":29,"foilPrice":0.38},{"name":"Ghitu Encampment","rarity":"Special","baseAvail":1666,"basePrice":0.01,"foilAvail":51,"foilPrice":1.75},{"name":"Ghitu Fire-Eater","rarity":"Special","baseAvail":1157,"basePrice":0.01,"foilAvail":55,"foilPrice":0.15},{"name":"Ghitu Slinger","rarity":"Special","baseAvail":2140,"basePrice":0.01,"foilAvail":30,"foilPrice":0.3},{"name":"Ghitu War Cry","rarity":"Special","baseAvail":1083,"basePrice":0.02,"foilAvail":52,"foilPrice":0.25},{"name":"Giant Cockroach","rarity":"Special","baseAvail":1727,"basePrice":0.01,"foilAvail":65,"foilPrice":0.05},{"name":"Goblin Medics","rarity":"Special","baseAvail":1713,"basePrice":0.01,"foilAvail":21,"foilPrice":0.2},{"name":"Goblin Welder","rarity":"Special","baseAvail":1011,"basePrice":1,"foilAvail":33,"foilPrice":30},{"name":"Granite Grip","rarity":"Special","baseAvail":1737,"basePrice":0.01,"foilAvail":63,"foilPrice":0.15},{"name":"Grim Monolith","rarity":"Special","baseAvail":330,"basePrice":69.99,"foilAvail":19,"foilPrice":549.95},{"name":"Harmonic Convergence","rarity":"Special","baseAvail":1404,"basePrice":0.02,"foilAvail":63,"foilPrice":0.5},{"name":"Hidden Gibbons","rarity":"Special","baseAvail":855,"basePrice":0.05,"foilAvail":30,"foilPrice":3.9},{"name":"Hope and Glory","rarity":"Special","baseAvail":1131,"basePrice":0.02,"foilAvail":38,"foilPrice":0.2},{"name":"Impending Disaster","rarity":"Special","baseAvail":539,"basePrice":0.19,"foilAvail":24,"foilPrice":13},{"name":"Intervene","rarity":"Special","baseAvail":1871,"basePrice":0.01,"foilAvail":37,"foilPrice":0.22},{"name":"Iron Maiden","rarity":"Special","baseAvail":523,"basePrice":0.07,"foilAvail":33,"foilPrice":19},{"name":"Iron Will","rarity":"Special","baseAvail":1763,"basePrice":0.01,"foilAvail":41,"foilPrice":0.15},{"name":"Jhoira's Toolbox","rarity":"Special","baseAvail":1019,"basePrice":0.02,"foilAvail":15,"foilPrice":0.75},{"name":"Karmic Guide","rarity":"Special","baseAvail":642,"basePrice":0.8,"foilAvail":23,"foilPrice":58.95},{"name":"King Crab","rarity":"Special","baseAvail":1083,"basePrice":0.02,"foilAvail":36,"foilPrice":0.34},{"name":"Knighthood","rarity":"Special","baseAvail":980,"basePrice":0.02,"foilAvail":59,"foilPrice":0.23},{"name":"Last-Ditch Effort","rarity":"Special","baseAvail":952,"basePrice":0.01,"foilAvail":17,"foilPrice":0.45},{"name":"Lava Axe","rarity":"Special","baseAvail":1792,"basePrice":0.01,"foilAvail":50,"foilPrice":0.2},{"name":"Levitation","rarity":"Special","baseAvail":1122,"basePrice":0.02,"foilAvail":51,"foilPrice":0.38},{"name":"Lone Wolf","rarity":"Special","baseAvail":979,"basePrice":0.01,"foilAvail":4,"foilPrice":2.25},{"name":"Lurking Skirge","rarity":"Special","baseAvail":874,"basePrice":0.02,"foilAvail":34,"foilPrice":0.99},{"name":"Martyr's Cause","rarity":"Special","baseAvail":881,"basePrice":0.02,"foilAvail":21,"foilPrice":1.45},{"name":"Memory Jar","rarity":"Special","baseAvail":348,"basePrice":16.86,"foilAvail":23,"foilPrice":111},{"name":"Might of Oaks","rarity":"Special","baseAvail":504,"basePrice":0.02,"foilAvail":37,"foilPrice":11},{"name":"Miscalculation","rarity":"Special","baseAvail":2396,"basePrice":0.02,"foilAvail":38,"foilPrice":19.99},{"name":"Molten Hydra","rarity":"Special","baseAvail":792,"basePrice":0.03,"foilAvail":8,"foilPrice":2.99},{"name":"Mother of Runes","rarity":"Special","baseAvail":1378,"basePrice":0.75,"foilAvail":51,"foilPrice":20.71},{"name":"Multani, Maro-Sorcerer","rarity":"Special","baseAvail":322,"basePrice":0.2,"foilAvail":22,"foilPrice":65},{"name":"Multani's Acolyte","rarity":"Special","baseAvail":2032,"basePrice":0.01,"foilAvail":38,"foilPrice":0.39},{"name":"Multani's Presence","rarity":"Special","baseAvail":1269,"basePrice":0.02,"foilAvail":31,"foilPrice":0.8},{"name":"No Mercy","rarity":"Special","baseAvail":282,"basePrice":6,"foilAvail":15,"foilPrice":24.99},{"name":"Opal Avenger","rarity":"Special","baseAvail":913,"basePrice":0.02,"foilAvail":29,"foilPrice":1.79},{"name":"Opal Champion","rarity":"Special","baseAvail":2005,"basePrice":0.01,"foilAvail":58,"foilPrice":0.1},{"name":"Opportunity","rarity":"Special","baseAvail":2031,"basePrice":0.01,"foilAvail":54,"foilPrice":1.5},{"name":"Ostracize","rarity":"Special","baseAvail":2149,"basePrice":0.02,"foilAvail":41,"foilPrice":0.49},{"name":"Palinchron","rarity":"Special","baseAvail":256,"basePrice":11,"foilAvail":25,"foilPrice":140},{"name":"Parch","rarity":"Special","baseAvail":1987,"basePrice":0.01,"foilAvail":54,"foilPrice":0.15},{"name":"Peace and Quiet","rarity":"Special","baseAvail":1115,"basePrice":0.02,"foilAvail":31,"foilPrice":0.3},{"name":"Phyrexian Broodlings","rarity":"Special","baseAvail":1785,"basePrice":0.01,"foilAvail":48,"foilPrice":0.15},{"name":"Phyrexian Debaser","rarity":"Special","baseAvail":1917,"basePrice":0.01,"foilAvail":47,"foilPrice":0.15},{"name":"Phyrexian Defiler","rarity":"Special","baseAvail":1366,"basePrice":0.02,"foilAvail":34,"foilPrice":0.2},{"name":"Phyrexian Denouncer","rarity":"Special","baseAvail":1905,"basePrice":0.01,"foilAvail":56,"foilPrice":0.15},{"name":"Phyrexian Plaguelord","rarity":"Special","baseAvail":974,"basePrice":0.04,"foilAvail":20,"foilPrice":9.99},{"name":"Phyrexian Reclamation","rarity":"Special","baseAvail":465,"basePrice":0.02,"foilAvail":31,"foilPrice":20},{"name":"Plague Beetle","rarity":"Special","baseAvail":1707,"basePrice":0.01,"foilAvail":62,"foilPrice":0.04},{"name":"Planar Collapse","rarity":"Special","baseAvail":663,"basePrice":0.2,"foilAvail":40,"foilPrice":19},{"name":"Purify","rarity":"Special","baseAvail":812,"basePrice":0.1,"foilAvail":26,"foilPrice":4.99},{"name":"Pygmy Pyrosaur","rarity":"Special","baseAvail":1717,"basePrice":0.01,"foilAvail":49,"foilPrice":0.09},{"name":"Pyromancy","rarity":"Special","baseAvail":717,"basePrice":0.09,"foilAvail":24,"foilPrice":5},{"name":"Quicksilver Amulet","rarity":"Special","baseAvail":444,"basePrice":2.98,"foilAvail":29,"foilPrice":23.95},{"name":"Rack and Ruin","rarity":"Special","baseAvail":2337,"basePrice":0.02,"foilAvail":110,"foilPrice":0.99},{"name":"Radiant, Archangel","rarity":"Special","baseAvail":424,"basePrice":0.6,"foilAvail":14,"foilPrice":59.9},{"name":"Radiant's Dragoons","rarity":"Special","baseAvail":1444,"basePrice":0.02,"foilAvail":52,"foilPrice":0.45},{"name":"Radiant's Judgment","rarity":"Special","baseAvail":2293,"basePrice":0.01,"foilAvail":38,"foilPrice":0.2},{"name":"Rancor","rarity":"Special","baseAvail":1205,"basePrice":0.2,"foilAvail":59,"foilPrice":11},{"name":"Rank and File","rarity":"Special","baseAvail":1139,"basePrice":0.02,"foilAvail":34,"foilPrice":0.35},{"name":"Raven Familiar","rarity":"Special","baseAvail":1767,"basePrice":0.02,"foilAvail":51,"foilPrice":1.8},{"name":"Rebuild","rarity":"Special","baseAvail":1465,"basePrice":0.02,"foilAvail":86,"foilPrice":2.75},{"name":"Repopulate","rarity":"Special","baseAvail":1791,"basePrice":0.01,"foilAvail":42,"foilPrice":0.25},{"name":"Ring of Gix","rarity":"Special","baseAvail":640,"basePrice":0.05,"foilAvail":31,"foilPrice":45},{"name":"Rivalry","rarity":"Special","baseAvail":921,"basePrice":0.04,"foilAvail":27,"foilPrice":1.5},{"name":"Scrapheap","rarity":"Special","baseAvail":824,"basePrice":0.02,"foilAvail":29,"foilPrice":1.99},{"name":"Second Chance","rarity":"Special","baseAvail":240,"basePrice":0.15,"foilAvail":19,"foilPrice":40},{"name":"Shivan Phoenix","rarity":"Special","baseAvail":779,"basePrice":0.08,"foilAvail":19,"foilPrice":7.99},{"name":"Sick and Tired","rarity":"Special","baseAvail":1822,"basePrice":0.01,"foilAvail":75,"foilPrice":0.1},{"name":"Silk Net","rarity":"Special","baseAvail":1933,"basePrice":0.01,"foilAvail":75,"foilPrice":0.15},{"name":"Simian Grunts","rarity":"Special","baseAvail":2108,"basePrice":0.01,"foilAvail":21,"foilPrice":0.75},{"name":"Sleeper's Guile","rarity":"Special","baseAvail":1630,"basePrice":0.01,"foilAvail":42,"foilPrice":0.17},{"name":"Slow Motion","rarity":"Special","baseAvail":1897,"basePrice":0.01,"foilAvail":29,"foilPrice":0.6},{"name":"Sluggishness","rarity":"Special","baseAvail":1767,"basePrice":0.01,"foilAvail":51,"foilPrice":0.15},{"name":"Snap","rarity":"Special","baseAvail":1568,"basePrice":0.2,"foilAvail":47,"foilPrice":9.95},{"name":"Spawning Pool","rarity":"Special","baseAvail":1382,"basePrice":0.02,"foilAvail":34,"foilPrice":1.48},{"name":"Subversion","rarity":"Special","baseAvail":526,"basePrice":0.05,"foilAvail":24,"foilPrice":4},{"name":"Sustainer of the Realm","rarity":"Special","baseAvail":1319,"basePrice":0.02,"foilAvail":20,"foilPrice":0.5},{"name":"Swat","rarity":"Special","baseAvail":1872,"basePrice":0.01,"foilAvail":58,"foilPrice":0.25},{"name":"Tethered Skirge","rarity":"Special","baseAvail":1269,"basePrice":0.01,"foilAvail":39,"foilPrice":0.19},{"name":"Thornwind Faeries","rarity":"Special","baseAvail":2060,"basePrice":0.01,"foilAvail":38,"foilPrice":0.75},{"name":"Thran Lens","rarity":"Special","baseAvail":825,"basePrice":0.08,"foilAvail":24,"foilPrice":1},{"name":"Thran War Machine","rarity":"Special","baseAvail":1198,"basePrice":0.02,"foilAvail":37,"foilPrice":0.19},{"name":"Thran Weaponry","rarity":"Special","baseAvail":925,"basePrice":0.05,"foilAvail":23,"foilPrice":1.98},{"name":"Ticking Gnomes","rarity":"Special","baseAvail":1684,"basePrice":0.02,"foilAvail":31,"foilPrice":0.25},{"name":"Tinker","rarity":"Special","baseAvail":1153,"basePrice":0.98,"foilAvail":47,"foilPrice":10},{"name":"Tragic Poet","rarity":"Special","baseAvail":1798,"basePrice":0.01,"foilAvail":38,"foilPrice":0.45},{"name":"Treacherous Link","rarity":"Special","baseAvail":1173,"basePrice":0.01,"foilAvail":29,"foilPrice":0.4},{"name":"Treefolk Mystic","rarity":"Special","baseAvail":1742,"basePrice":0.01,"foilAvail":53,"foilPrice":0.05},{"name":"Treetop Village","rarity":"Special","baseAvail":995,"basePrice":0.05,"foilAvail":8,"foilPrice":34.99},{"name":"Unearth","rarity":"Special","baseAvail":1147,"basePrice":0.4,"foilAvail":67,"foilPrice":17.99},{"name":"Urza's Blueprints","rarity":"Special","baseAvail":1199,"basePrice":0.04,"foilAvail":34,"foilPrice":2.39},{"name":"Viashino Bey","rarity":"Special","baseAvail":1804,"basePrice":0.01,"foilAvail":76,"foilPrice":0.15},{"name":"Viashino Cutthroat","rarity":"Special","baseAvail":1433,"basePrice":0.01,"foilAvail":47,"foilPrice":0.21},{"name":"Viashino Heretic","rarity":"Special","baseAvail":1083,"basePrice":0.02,"foilAvail":58,"foilPrice":2.5},{"name":"Viashino Sandscout","rarity":"Special","baseAvail":1890,"basePrice":0.01,"foilAvail":61,"foilPrice":0.12},{"name":"Vigilant Drake","rarity":"Special","baseAvail":1847,"basePrice":0.01,"foilAvail":41,"foilPrice":0.1},{"name":"Walking Sponge","rarity":"Special","baseAvail":1261,"basePrice":0.01,"foilAvail":49,"foilPrice":0.27},{"name":"Weatherseed Elf","rarity":"Special","baseAvail":1793,"basePrice":0.01,"foilAvail":56,"foilPrice":0.2},{"name":"Weatherseed Faeries","rarity":"Special","baseAvail":1849,"basePrice":0.01,"foilAvail":26,"foilPrice":0.6},{"name":"Weatherseed Treefolk","rarity":"Special","baseAvail":729,"basePrice":0.04,"foilAvail":20,"foilPrice":34.99},{"name":"Wheel of Torture","rarity":"Special","baseAvail":673,"basePrice":0.05,"foilAvail":27,"foilPrice":2.95},{"name":"Wing Snare","rarity":"Special","baseAvail":1189,"basePrice":0.02,"foilAvail":48,"foilPrice":0.1},{"name":"Yavimaya Granger","rarity":"Special","baseAvail":2045,"basePrice":0.01,"foilAvail":33,"foilPrice":1.1},{"name":"Yavimaya Scion","rarity":"Special","baseAvail":1814,"basePrice":0.01,"foilAvail":50,"foilPrice":0.14},{"name":"Yavimaya Wurm","rarity":"Special","baseAvail":1658,"basePrice":0.01,"foilAvail":41,"foilPrice":0.25}]}
]}